slotrepr/__init__.py
slotrepr/core/__init__.py
slotrepr/tests/__init__.py
slotrepr/tests/test_easy.py
slotrepr-1.0.0.dist-info/LICENSE.txt
slotrepr-1.0.0.dist-info/METADATA
slotrepr-1.0.0.dist-info/WHEEL
slotrepr-1.0.0.dist-info/top_level.txt
slotrepr-1.0.0.dist-info/RECORD
