Metadata-Version: 2.2
Name: slotrepr
Version: 1.0.0
Summary: This project allows for easy common-sense __repr__ methods.
Author-email: Johannes <johannes-programming@mailfence.com>
License: The MIT License (MIT)
Project-URL: Download, https://pypi.org/project/slotrepr/#files
Project-URL: Index, https://pypi.org/project/slotrepr/
Project-URL: Source, https://github.com/johannes-programming/slotrepr/
Project-URL: Website, https://slotrepr.johannes-programming.online/
Classifier: Development Status :: 5 - Production/Stable
Classifier: License :: OSI Approved :: MIT License
Classifier: Natural Language :: English
Classifier: Operating System :: OS Independent
Classifier: Programming Language :: Python
Classifier: Programming Language :: Python :: 3
Classifier: Programming Language :: Python :: 3 :: Only
Requires-Python: >=3.8
License-File: LICENSE.txt
